custom_logger/__init__.py
custom_logger/logger.py
drnerd1_logger-1.0.2.dist-info/licenses/LICENSE
drnerd1_logger-1.0.2.dist-info/METADATA
drnerd1_logger-1.0.2.dist-info/WHEEL
drnerd1_logger-1.0.2.dist-info/top_level.txt
drnerd1_logger-1.0.2.dist-info/RECORD
