Metadata-Version: 2.4
Name: drnerd1-logger
Version: 1.0.2
Summary: A custom colored logger with ANSI support
Author-email: Ron Roitburg <ronroitburg@gmail.com>
License: MIT
Requires-Python: >=3.8
License-File: LICENSE
Requires-Dist: colorlog
Requires-Dist: colorama
Dynamic: license-file
